MANIFEST.in
README.rst
setup.py
diamond/__init__.py
diamond/glms/__init__.py
diamond/glms/cumulative_logistic.py
diamond/glms/glm.py
diamond/glms/logistic.py
diamond/glms/tests/__init__.py
diamond/glms/tests/test_logistic.py
diamond/integration_tests/__init__.py
diamond/integration_tests/test_clogistic_simulated.py
diamond/integration_tests/test_logistic_simulated.py
diamond/solvers/__init__.py
diamond/solvers/diamond_cumulative_logistic.py
diamond/solvers/diamond_logistic.py
diamond/solvers/repeated_block_diag.py
diamond/solvers/repeated_block_dot.c
diamond/solvers/repeated_block_dot.pyx
diamond/solvers/utils.py
sf_diamond.egg-info/PKG-INFO
sf_diamond.egg-info/SOURCES.txt
sf_diamond.egg-info/dependency_links.txt
sf_diamond.egg-info/requires.txt
sf_diamond.egg-info/top_level.txt