Metadata-Version: 1.0
Name: sf-diamond
Version: 0.2.2
Summary: GLMMs with known variances in python with Newton-like solver
Home-page: http://github.com/stitchfix/diamond
Author: ['Aaron Bradley', 'Timothy Sweetser']
Author-email: ['abradley@stitchfix.com', 'tsweetser@stitchfix.com']
License: LICENSE.txt
Platform: UNKNOWN
